Metadata-Version: 2.1
Name: odoo12-addon-account_cutoff_prepaid
Version: 12.0.1.0.0.99.dev32
Summary: Prepaid Expense, Prepaid Revenue
Home-page: https://github.com/OCA/account-closing
Author: Akretion,Odoo Community Association (OCA)
Author-email: support@odoo-community.org
License: AGPL-3
Classifier: Programming Language :: Python
Classifier: Framework :: Odoo
Classifier: Framework :: Odoo :: 12.0
Classifier: License :: OSI Approved :: GNU Affero General Public License v3
Requires-Python: >=3.5
Requires-Dist: odoo12-addon-account-cutoff-base
Requires-Dist: odoo12-addon-account-invoice-start-end-dates
Requires-Dist: odoo<12.1dev,>=12.0a
